{
	"credit": "Made with Blockbench",
	"ambientocclusion": false,
	"textures": {
		"0": "furenikusroads:block/paints/line_straight_double_0",
		"particle": "furenikusroads:block/paints/line_straight_double_0"
	},
	"elements": [
		{
			"from": [0, -11, 6],
			"to": [16, -10.5, 10],
			"rotation": {"angle": 0, "axis": "y", "origin": [0, 15, 12]},
			"faces": {
				"north": {"uv": [10, 0, 11, 0.5], "texture": "#0"},
				"east": {"uv": [5, 0, 7, 0.5], "texture": "#0"},
				"south": {"uv": [5, 0, 7, 0.5], "texture": "#0"},
				"west": {"uv": [5, 0, 7, 0.5], "texture": "#0"},
				"up": {"uv": [5, 0, 7, 16], "rotation": 270, "texture": "#0"},
				"down": {"uv": [5, 0, 7, 16], "rotation": 90, "texture": "#0"}
			}
		},
		{
			"from": [6, -11, 0],
			"to": [10, -10.5, 16],
			"rotation": {"angle": 0, "axis": "y", "origin": [7, 15, 0]},
			"faces": {
				"north": {"uv": [5, 0, 7, 0.5], "texture": "#0"},
				"east": {"uv": [5, 0, 7, 0.5], "texture": "#0"},
				"south": {"uv": [5, 0, 7, 0.5], "texture": "#0"},
				"west": {"uv": [5, 2, 7, 3.5], "texture": "#0"},
				"up": {"uv": [5, 0, 7, 10], "texture": "#0"},
				"down": {"uv": [5, 0, 7, 10], "texture": "#0"}
			}
		}
	],
	"display": {
		"thirdperson_righthand": {
			"translation": [0, 6.25, 0],
			"scale": [0.6, 0.6, 0.6]
		},
		"thirdperson_lefthand": {
			"translation": [3.25, 10, 0],
			"scale": [0.625, 0.625, 0.625]
		},
		"firstperson_righthand": {
			"rotation": [30, 45, 0],
			"translation": [2.25, 6, 0.75],
			"scale": [0.625, 0.625, 0.625]
		}
	},
	"groups": [
		{
			"name": "group",
			"origin": [8, 8, 8],
			"color": 0,
			"children": [0, 1]
		}
	]
}